coder_code/__init__.py
coder_code/cli.py
coder_code/main.py
coder_code-0.2.1.dist-info/METADATA
coder_code-0.2.1.dist-info/WHEEL
coder_code-0.2.1.dist-info/entry_points.txt
coder_code-0.2.1.dist-info/RECORD
