Metadata-Version: 2.4
Name: coder-code
Version: 0.2.1
Author-email: Kevin Fortier <kevin.r.fortier@gmail.com>
Requires-Python: >=3.9
Requires-Dist: openai>=0.27.5
Requires-Dist: typer[all]>=0.7.0
